[
  {
    "title": "La pasta fredda più sottovalutata dell’estate",
    "link": "https://www.gamberorosso.it/notizie/rubriche/storie/pasta-alla-checca-pasta-fredda-estate/",
    "date": "2026-07-19T09:15:04.000Z"
  },
  {
    "title": "C’è un’abitudine a tavola che sta rovinando più coppie di quanto immagini",
    "link": "https://www.gamberorosso.it/notizie/rubriche/storie/foodie-gap-cibo-crisi-coppia/",
    "date": "2026-07-19T09:10:41.000Z"
  },
  {
    "title": "Se sei cresciuto negli anni Duemila, questa bottiglietta l’hai bevuta almeno una volta",
    "link": "https://www.gamberorosso.it/notizie/rubriche/storie/bacardi-breezer-prima-sbronza-millennials/",
    "date": "2026-07-19T07:56:05.000Z"
  },
  {
    "title": "Apre il ristorante di una delle cantine più affascinanti d’Italia",
    "link": "https://www.gamberorosso.it/rubriche/nuove-aperture/apre-il-ristorante-di-una-delle-cantine-piu-affascinanti-ditalia/",
    "date": "2026-07-19T07:55:14.000Z"
  },
  {
    "title": "La terrazza di Roma dove il tramonto vale il prezzo della cena",
    "link": "https://www.gamberorosso.it/notizie/ristoranti/terrazza-roma-tramonto-acquaroof-recensione/",
    "date": "2026-07-19T07:49:56.000Z"
  }
]